jenkins_mcp_server/__init__.py
jenkins_mcp_server/__main__.py
jenkins_mcp_server/exceptions.py
jenkins_mcp_server/models.py
jenkins_mcp_server/server.py
jenkins_mcp_server/handlers/__init__.py
jenkins_mcp_server/handlers/base_handler.py
jenkins_mcp_server/handlers/build_handler.py
jenkins_mcp_server/handlers/job_handler.py
jenkins_mcp_server/handlers/pipeline_handler.py
jenkins_mcp_server/handlers/system_handler.py
jenkins_mcp_server/utils/__init__.py
jenkins_mcp_server/utils/cache.py
jenkins_mcp_server/utils/connection_pool.py
jenkins_mcp_server/utils/error_reporting.py
jenkins_mcp_server/utils/logging_helper.py
jenkins_mcp_server/utils/path_utils.py
jenkins_mcp_server/utils/pipeline_utils.py
jenkins_mcp_server/utils/retry.py
jenkins_mcp_server/utils/validation.py
cloudthat_jenkins_mcp_server-1.0.3.dist-info/METADATA
cloudthat_jenkins_mcp_server-1.0.3.dist-info/WHEEL
cloudthat_jenkins_mcp_server-1.0.3.dist-info/entry_points.txt
cloudthat_jenkins_mcp_server-1.0.3.dist-info/licenses/LICENSE
cloudthat_jenkins_mcp_server-1.0.3.dist-info/RECORD
