Metadata-Version: 2.4
Name: cloudthat.jenkins-mcp-server
Version: 1.0.3
Summary: A Model Context Protocol (MCP) server for Jenkins CI/CD integration
Project-URL: Homepage, https://github.com/jenkins-mcp/jenkins-mcp-server
Project-URL: Documentation, https://github.com/jenkins-mcp/jenkins-mcp-server#readme
Project-URL: Source, https://github.com/jenkins-mcp/jenkins-mcp-server
Project-URL: Bug Tracker, https://github.com/jenkins-mcp/jenkins-mcp-server/issues
Author-email: Jenkins MCP Team <jenkins-mcp@example.com>
License: Proprietary
License-File: LICENSE
Classifier: License :: Other/Proprietary License
Classifier: Operating System :: OS Independent
Classifier: Programming Language :: Python
Classifier: Programming Language :: Python :: 3
Classifier: Programming Language :: Python :: 3.10
Classifier: Programming Language :: Python :: 3.11
Classifier: Programming Language :: Python :: 3.12
Classifier: Programming Language :: Python :: 3.13
Requires-Python: >=3.10
Requires-Dist: cachetools>=5.3.0
Requires-Dist: httpx>=0.27.0
Requires-Dist: jenkinsapi>=0.3.14
Requires-Dist: loguru>=0.7.0
Requires-Dist: mcp[cli]>=1.6.0
Requires-Dist: pydantic>=2.10.6
Requires-Dist: python-dotenv>=1.0.1
Requires-Dist: python-jenkins>=1.8.0
Requires-Dist: tenacity>=8.2.0
